odoo/addons/partner_stage/README.rst
odoo/addons/partner_stage/__init__.py
odoo/addons/partner_stage/__manifest__.py
odoo/addons/partner_stage/init_hook.py
odoo/addons/partner_stage/data/partner_stage_data.xml
odoo/addons/partner_stage/i18n/partner_stage.pot
odoo/addons/partner_stage/models/__init__.py
odoo/addons/partner_stage/models/res_partner.py
odoo/addons/partner_stage/models/res_partner_stage.py
odoo/addons/partner_stage/readme/CONFIGURATION.rst
odoo/addons/partner_stage/readme/CONTRIBUTORS.rst
odoo/addons/partner_stage/readme/DESCRIPTION.rst
odoo/addons/partner_stage/readme/USAGE.rst
odoo/addons/partner_stage/security/ir.model.access.csv
odoo/addons/partner_stage/static/description/icon.png
odoo/addons/partner_stage/static/description/index.html
odoo/addons/partner_stage/tests/__init__.py
odoo/addons/partner_stage/tests/test_partner_stage.py
odoo/addons/partner_stage/views/res_partner_stage_views.xml
odoo/addons/partner_stage/views/res_partner_views.xml
odoo12_addon_partner_stage-12.0.1.0.0.99.dev1.dist-info/METADATA
odoo12_addon_partner_stage-12.0.1.0.0.99.dev1.dist-info/WHEEL
odoo12_addon_partner_stage-12.0.1.0.0.99.dev1.dist-info/top_level.txt
odoo12_addon_partner_stage-12.0.1.0.0.99.dev1.dist-info/RECORD
