Metadata-Version: 2.1
Name: odoo12-addon-partner_stage
Version: 12.0.1.0.0.99.dev1
Summary: Add lifecycle Stages to Partners
Home-page: https://github.com/OCA/partner-contact
Author: Open Source Integrators, Odoo Community Association (OCA)
Author-email: support@odoo-community.org
License: AGPL-3
Classifier: Programming Language :: Python
Classifier: Framework :: Odoo
Classifier: Framework :: Odoo :: 12.0
Classifier: License :: OSI Approved :: GNU Affero General Public License v3
Requires-Python: >=3.5
Requires-Dist: odoo<12.1dev,>=12.0a
